sandlertools/__init__.py
sandlertools/cli.py
sandlertools-0.5.1.dist-info/METADATA
sandlertools-0.5.1.dist-info/WHEEL
sandlertools-0.5.1.dist-info/entry_points.txt
sandlertools-0.5.1.dist-info/licenses/LICENSE
sandlertools-0.5.1.dist-info/RECORD
