Metadata-Version: 2.4
Name: sandlertools
Version: 0.5.1
Summary: A metapackage combining several computational tools based on Chemical, Biochemical, and Engineering Thermodynamics (5th edition) by Stan Sandler
Author-email: Cameron F Abrams <cfa22@drexel.edu>
License-File: LICENSE
Classifier: License :: OSI Approved :: MIT License
Classifier: Programming Language :: Python :: 3
Requires-Python: >=3.7
Requires-Dist: numpy
Requires-Dist: sandlerchemeq>=0.1.0
Requires-Dist: sandlercorrespondingstates>=0.1.0
Requires-Dist: sandlercubics>=0.2.0
Requires-Dist: sandlermisc>=0.2.1
Requires-Dist: sandlerprops>=0.2.0
Requires-Dist: sandlersteam>=0.5.0
Requires-Dist: scipy
